streetwise/__init__.py
streetwise/apps.py
streetwise/blocks.py
streetwise/model_porter.py
streetwise/models.py
streetwise/migrations/0001_initial.py
streetwise/migrations/__init__.py
streetwise/static/streetwise/css/streetwise.css
streetwise/static/streetwise/css/streetwise.css.map
streetwise/static/streetwise/css/images/layers-2x.png
streetwise/static/streetwise/css/images/layers.png
streetwise/static/streetwise/css/images/marker-icon-2x.png
streetwise/static/streetwise/css/images/marker-icon.png
streetwise/static/streetwise/css/images/marker-shadow.png
streetwise/static/streetwise/js/leaflet-src.js.map
streetwise/static/streetwise/js/leaflet.js.map
streetwise/static/streetwise/js/streetwise.js
streetwise/static/streetwise/js/streetwise.js.map
streetwise/templates/streetwise/blocks/leaflet_viewer_block.html
streetwise/templates/streetwise/tags/support.html
streetwise/templatetags/__init__.py
streetwise/templatetags/streetwise_tags.py
streetwise-4.1.0.dist-info/AUTHORS.txt
streetwise-4.1.0.dist-info/LICENSE.txt
streetwise-4.1.0.dist-info/METADATA
streetwise-4.1.0.dist-info/WHEEL
streetwise-4.1.0.dist-info/top_level.txt
streetwise-4.1.0.dist-info/zip-safe
streetwise-4.1.0.dist-info/RECORD
