Metadata-Version: 2.1
Name: streetwise
Version: 4.1.0
Summary: A Wagtail app for maps based on media-catalogue.
Home-page: https://github.com/high-dimensional/streetwise
Author: High Dimensional Neurology Group, UCL
Author-email: pypi@highdimensional.net
License: BSD-3-Clause
Platform: any
Classifier: Framework :: Django
Classifier: Framework :: Wagtail
Classifier: Programming Language :: Python :: 3
Classifier: Programming Language :: Python :: 3.8
Classifier: License :: OSI Approved :: BSD License
Classifier: Operating System :: OS Independent
Requires-Python: >=3.8
License-File: LICENSE.txt
License-File: AUTHORS.txt
Requires-Dist: Django (<4.2,>=4.1)
Requires-Dist: wagtail (<4.2,>=4.1)
Requires-Dist: django-auxiliaries (<4.2,>=4.1)
Requires-Dist: model-porter (<4.2,>=4.1)
Requires-Dist: wagtail-richer-text (<4.2,>=4.1)
Requires-Dist: media-catalogue (<4.2,>=4.1.2)
